gis_mcp/__init__.py
gis_mcp/config.py
gis_mcp/server.py
gis_mcp/utils.py
gis_mcp/tools/__init__.py
gis_mcp/tools/elevation.py
gis_mcp/tools/files.py
gis_mcp/tools/geocoding.py
gis_mcp/tools/geometry.py
gis_mcp/tools/raster.py
gis_mcp/tools/routing.py
gis_mcp/tools/statistics.py
gis_mcp/tools/visualization.py
gis_mcp_server-1.2.0.dist-info/METADATA
gis_mcp_server-1.2.0.dist-info/WHEEL
gis_mcp_server-1.2.0.dist-info/entry_points.txt
gis_mcp_server-1.2.0.dist-info/licenses/LICENSE
gis_mcp_server-1.2.0.dist-info/RECORD
