Metadata-Version: 2.4
Name: gis-mcp-server
Version: 1.2.0
Summary: MCP Server for geospatial operations - geocoding, routing, spatial analysis
Project-URL: Homepage, https://github.com/matbel91765/gis-mcp-server
Project-URL: Documentation, https://github.com/matbel91765/gis-mcp-server#readme
Project-URL: Repository, https://github.com/matbel91765/gis-mcp-server
Project-URL: Issues, https://github.com/matbel91765/gis-mcp-server/issues
Author: GIS MCP Team
License-Expression: MIT
License-File: LICENSE
Keywords: geocoding,geopandas,geospatial,gis,mcp,nominatim,osrm,routing,shapely
Classifier: Development Status :: 3 - Alpha
Classifier: Intended Audience :: Developers
Classifier: License :: OSI Approved :: MIT License
Classifier: Programming Language :: Python :: 3
Classifier: Programming Language :: Python :: 3.11
Classifier: Programming Language :: Python :: 3.12
Classifier: Topic :: Scientific/Engineering :: GIS
Requires-Python: >=3.11
Requires-Dist: aiohttp>=3.9.0
Requires-Dist: fastmcp>=0.1.0
Requires-Dist: fiona>=1.9.0
Requires-Dist: geopandas>=0.14.0
Requires-Dist: geopy>=2.4.0
Requires-Dist: numpy>=1.24.0
Requires-Dist: pydantic>=2.0.0
Requires-Dist: pyproj>=3.6.0
Requires-Dist: rasterio>=1.3.0
Requires-Dist: shapely>=2.0.0
Provides-Extra: all
Requires-Dist: esda>=2.4.0; extra == 'all'
Requires-Dist: folium>=0.14.0; extra == 'all'
Requires-Dist: libpysal>=4.7.0; extra == 'all'
Requires-Dist: matplotlib>=3.7.0; extra == 'all'
Provides-Extra: dev
Requires-Dist: mypy>=1.5.0; extra == 'dev'
Requires-Dist: pytest-asyncio>=0.21.0; extra == 'dev'
Requires-Dist: pytest-cov>=4.1.0; extra == 'dev'
Requires-Dist: pytest>=7.4.0; extra == 'dev'
Requires-Dist: ruff>=0.1.0; extra == 'dev'
Provides-Extra: statistics
Requires-Dist: esda>=2.4.0; extra == 'statistics'
Requires-Dist: libpysal>=4.7.0; extra == 'statistics'
Provides-Extra: visualization
Requires-Dist: folium>=0.14.0; extra == 'visualization'
Requires-Dist: matplotlib>=3.7.0; extra == 'visualization'
